{
  "parent": "item/generated",
  "loader": "soulbound:wand",
  "textures": {
    "particle": "soulbound:item/wands/wand"
  },
  "wand": {
    "wand": "soulbound:item/wands/wand",

    "seals": [{
      "type": "passive",
      "textures": {
        "pickaxing": "soulbound:item/wands/activated/pickaxing",
        "shoveling": "soulbound:item/wands/activated/axing"
      }
    }, {
      "type": "offensive",
      "textures": {
        "axing": "soulbound:item/wands/activated/axing",
        "scythe": "soulbound:item/wands/activated/scythe"
      }
    }]
  }
}